qA_Ap/__init__.py
qA_Ap/app/__init__.py
qA_Ap/app/catalog.py
qA_Ap/app/methods.py
qA_Ap/app/ai/__init__.py
qA_Ap/app/ai/faissvectorstore.py
qA_Ap/app/ai/methods.py
qA_Ap/app/ai/interfaces/__init__.py
qA_Ap/app/ai/interfaces/cerebras.py
qA_Ap/app/ai/interfaces/ollama.py
qA_Ap/classes/__init__.py
qA_Ap/classes/errors/__init__.py
qA_Ap/classes/errors/db.py
qA_Ap/cli/__init__.py
qA_Ap/db/__init__.py
qA_Ap/db/baserowfreeapidb.py
qA_Ap/db/flatfiledb.py
qA_Ap/globals/__init__.py
qA_Ap/web/__init__.py
qA_Ap/web/api.py
qA_Ap/web/api_docs.html
qA_Ap/web/frontend/boot.css
qA_Ap/web/frontend/icon.png
qA_Ap/web/frontend/index.html
qA_Ap/web/frontend/qaap.js
qA_Ap/web/frontend/script.js
qA_Ap/web/frontend/style.css
qa_ap-0.2.9.1.dist-info/METADATA
qa_ap-0.2.9.1.dist-info/WHEEL
qa_ap-0.2.9.1.dist-info/entry_points.txt
qa_ap-0.2.9.1.dist-info/licenses/LICENSE
qa_ap-0.2.9.1.dist-info/RECORD
