Metadata-Version: 2.4
Name: qA_Ap
Version: 0.2.9.1
Summary: query About Anything package: A Q&A application powered by LLMs and RAG on custom data.
Project-URL: Homepage, https://github.com/Fleurman/qA_Ap
Project-URL: Issues, https://github.com/Fleurman/qA_Ap/issues
Project-URL: Documentation, https://martin.surlesinternets.ch/qA_Ap/docs
Author-email: Martin Ashton-Lomax <ashtonlomaxmartin@gmail.com>
License-Expression: MIT
License-File: LICENSE
Classifier: Operating System :: OS Independent
Classifier: Programming Language :: Python :: 3
Requires-Python: >=3.12
Requires-Dist: bottle==0.13.4
Requires-Dist: cerebras-cloud-sdk==1.46.0
Requires-Dist: faiss-cpu==1.12.0
Requires-Dist: numpy==2.3.2
Requires-Dist: ollama==0.5.3
Requires-Dist: oyaml==1.0
Requires-Dist: safer==5.1.0
Requires-Dist: semantic-text-splitter==0.27.0
Requires-Dist: sentence-transformers==5.0.0
Provides-Extra: gpu
Requires-Dist: faiss>=1.5.3; extra == 'gpu'
